tracardi_string_operations/plugin.py
tracardi_string_operations/model/__init__.py
tracardi_string_operations/model/configuration.py
tracardi_string_operations/model/__pycache__/__init__.cpython-38.pyc
tracardi_string_operations/model/__pycache__/configuration.cpython-38.pyc
tracardi_string_operations/service/__init__.py
tracardi_string_operations/service/operations.py
tracardi_string_operations/service/__pycache__/__init__.cpython-38.pyc
tracardi_string_operations/service/__pycache__/operations.cpython-38.pyc
tracardi_string_operations/test/manual_test.py
tracardi_string_operations-0.6.0.dist-info/LICENSE.md
tracardi_string_operations-0.6.0.dist-info/METADATA
tracardi_string_operations-0.6.0.dist-info/WHEEL
tracardi_string_operations-0.6.0.dist-info/top_level.txt
tracardi_string_operations-0.6.0.dist-info/RECORD
