Metadata-Version: 2.1
Name: tracardi-string-operations
Version: 0.6.0
Summary: This plug-in is to make a string operations like: lowercase remove spaces split and other
Home-page: UNKNOWN
Author: Patryk Migaj
License: UNKNOWN
Keywords: tracardi,plugin
Platform: UNKNOWN
Classifier: Programming Language :: Python :: 3
Classifier: License :: OSI Approved :: MIT License
Classifier: Operating System :: OS Independent
Requires-Python: >=3.8
License-File: LICENSE.md
Requires-Dist: tracardi-plugin-sdk (>=0.6.22)
